Metadata-Version: 2.4
Name: adafruit-circuitpython-ble-lywsd03mmc
Version: 1.0.21
Summary: BLE Support for Xiaomi LYWSD03MMC Thermometer/Hygrometer
Author-email: Adafruit Industries <circuitpython@adafruit.com>
License: MIT
Project-URL: Homepage, https://github.com/adafruit/Adafruit_CircuitPython_BLE_LYWSD03MMC
Keywords: adafruit,blinka,circuitpython,micropython,ble_lywsd03mmc,ble,lywsd03mmc,xiaomi,mijia,thermometer,hygrometer
Classifier: Intended Audience :: Developers
Classifier: Topic :: Software Development :: Libraries
Classifier: Topic :: Software Development :: Embedded Systems
Classifier: Topic :: System :: Hardware
Classifier: License :: OSI Approved :: MIT License
Classifier: Programming Language :: Python :: 3
License-File: LICENSE
Requires-Dist: Adafruit-Blinka
Requires-Dist: adafruit-circuitpython-ble
Provides-Extra: optional
Dynamic: license-file
